auroravr/__init__.py
auroravr/gamelift.py
auroravr/main.py
auroravr-0.1.3.dist-info/METADATA
auroravr-0.1.3.dist-info/WHEEL
auroravr-0.1.3.dist-info/top_level.txt
auroravr-0.1.3.dist-info/RECORD
