Metadata-Version: 2.1
Name: auroravr
Version: 0.1.3
Summary: You can use it for communicate with aws gamelift
Home-page: https://www.auroravr.io/
Author: Auroravr
Author-email: hyunjun.jeon@ticketplace.com
License: MIT
Keywords: aurora,auroravr,gamelift
Platform: UNKNOWN
Requires-Python: >=3
Requires-Dist: boto3
